{"954696351":{"location":[46.7200386,-113.5767408],"ct":"US","tp":"CS","ts":"2024-07-31T14:50:12Z","tX":188,"tY":361,"tags":{"ele":"1107","gnis:feature_id":"1781524","leisure":"park","name":"Beavertail Hill State Park"}},"4943157252":{"location":[46.5733963,-113.6607406],"ct":"US","tp":"CS","ts":"2017-06-29T22:39:46Z","tX":188,"tY":361,"tags":{"name":"Grizzly Campground"}},"12115388038":{"location":[46.5881551,-113.668911],"ct":"US","tp":"CS","ts":"2024-08-16T16:44:46Z","tX":188,"tY":361,"tags":{"name":"Norton Campground"}}}