{"928708871":{"location":[-20.3700328,-47.9835488],"ct":"BR","tp":"CS","ts":"2022-08-13T23:53:01Z","tX":375,"tY":571,"tags":{"name":"Rancho Golfo"}},"928708872":{"location":[-20.3699831,-47.9822313],"ct":"BR","tp":"CS","ts":"2022-08-13T23:53:01Z","tX":375,"tY":571,"tags":{"name":"Rancho da Ilha Perdida"}},"5075738128":{"location":[-20.4063249,-47.999111],"ct":"BR","tp":"CS","ts":"2022-01-14T23:49:18Z","tX":375,"tY":571,"tags":{"name":"Cachoeira do córrego Santana"}},"9071519807":{"location":[-20.3777731,-47.9727238],"ct":"BR","tp":"CS","ts":"2022-04-23T13:16:12Z","tX":375,"tY":571,"tags":{"name":"Rancho do Quasidono"}},"9071519808":{"location":[-20.3785818,-47.9720114],"ct":"BR","tp":"CS","ts":"2022-04-23T13:16:12Z","tX":375,"tY":571,"tags":{"name":"Rancho Numssei"}},"9191896268":{"location":[-20.3582275,-48.0407667],"ct":"BR","tp":"CS","ts":"2022-04-23T12:46:02Z","tX":375,"tY":571,"tags":{"name":"Rancho Tatu Bolinha"}},"9191896269":{"location":[-20.3568105,-48.0404596],"ct":"BR","tp":"CS","ts":"2022-04-23T12:46:02Z","tX":375,"tY":571,"tags":{"name":"Rancho Liberdade"}},"9264128826":{"location":[-20.3458595,-48.0652121],"ct":"BR","tp":"CS","ts":"2022-04-23T12:46:02Z","tX":375,"tY":571,"tags":{"name":"Rancho Penergetic"}},"9264128827":{"location":[-20.346223,-48.0574586],"ct":"BR","tp":"CS","ts":"2022-04-23T12:46:02Z","tX":375,"tY":571,"tags":{"name":"Rancho Abelha"}},"9264128828":{"location":[-20.3466499,-48.0574955],"ct":"BR","tp":"CS","ts":"2022-04-23T12:46:02Z","tX":375,"tY":571,"tags":{"name":"Rancho Mizuki"}},"9264128829":{"location":[-20.349552,-48.0558218],"ct":"BR","tp":"CS","ts":"2022-04-23T12:46:02Z","tX":375,"tY":571,"tags":{"name":"Rancho Santa Luzia"}},"9264128830":{"location":[-20.3491309,-48.0562894],"ct":"BR","tp":"CS","ts":"2022-04-23T12:46:02Z","tX":375,"tY":571,"tags":{"name":"Rancho Cama de Couro"}},"9264128831":{"location":[-20.3499559,-48.0547941],"ct":"BR","tp":"CS","ts":"2022-04-23T12:46:02Z","tX":375,"tY":571,"tags":{"name":"Rancho Nossa Senhora"}},"9423470684":{"location":[-20.3563156,-48.040348],"ct":"BR","tp":"CS","ts":"2022-04-23T12:46:02Z","tX":375,"tY":571,"tags":{"name":"Rancho do monte"}},"9423470685":{"location":[-20.3554229,-48.0396307],"ct":"BR","tp":"CS","ts":"2022-04-23T12:46:02Z","tX":375,"tY":571,"tags":{"name":"Rancho Aparecida"}},"9687842860":{"location":[-20.3715847,-47.9874579],"ct":"BR","tp":"CS","ts":"2022-04-23T12:46:02Z","tX":375,"tY":571,"tags":{"name":"Rancho Leão"}},"9687842861":{"location":[-20.3675741,-47.9916367],"ct":"BR","tp":"CS","ts":"2022-04-23T12:46:02Z","tX":375,"tY":571,"tags":{"name":"Rancho Bambu"}},"9687842874":{"location":[-20.3645403,-47.9954187],"ct":"BR","tp":"CS","ts":"2022-04-23T12:46:02Z","tX":375,"tY":571,"tags":{"name":"Rancho Cocó"}},"9687842881":{"location":[-20.3646584,-47.9984147],"ct":"BR","tp":"CS","ts":"2022-04-23T12:46:02Z","tX":375,"tY":571,"tags":{"name":"Rancho Antero"}},"9687842882":{"location":[-20.3643089,-47.9981572],"ct":"BR","tp":"CS","ts":"2022-04-23T12:46:02Z","tX":375,"tY":571,"tags":{"name":"Casa Antero"}},"9687842892":{"location":[-20.3657994,-48.0296168],"ct":"BR","tp":"CS","ts":"2022-04-23T12:46:02Z","tX":375,"tY":571,"tags":{"name":"Rancho Boneca"}},"9687842893":{"location":[-20.3652494,-48.0335422],"ct":"BR","tp":"CS","ts":"2022-04-23T12:46:02Z","tX":375,"tY":571,"tags":{"name":"Rancho Abel"}},"9687898998":{"location":[-20.3814391,-47.9652183],"ct":"BR","tp":"CS","ts":"2022-04-23T13:16:12Z","tX":375,"tY":571,"tags":{"name":"Rancho Supersilo"}},"9828800304":{"location":[-20.3560282,-48.0400631],"ct":"BR","tp":"CS","ts":"2022-06-18T18:54:55Z","tX":375,"tY":571,"tags":{"name":"Rancho Tampa do Fogão"}},"9828800307":{"location":[-20.3546224,-48.039532],"ct":"BR","tp":"CS","ts":"2022-06-18T18:54:55Z","tX":375,"tY":571,"tags":{"name":"Rancho Vida Vazia"}},"9829033424":{"location":[-20.3525642,-48.046161],"ct":"BR","tp":"CS","ts":"2022-06-18T20:03:32Z","tX":375,"tY":571,"tags":{"name":"Rancho Caramujo"}},"9829033436":{"location":[-20.3515533,-48.0502916],"ct":"BR","tp":"CS","ts":"2022-06-18T20:03:32Z","tX":375,"tY":571,"tags":{"name":"Rancho Encanado"}},"10118723104":{"location":[-20.4671004,-47.9982342],"ct":"BR","tp":"CS","ts":"2022-10-21T13:12:52Z","tX":375,"tY":571,"tags":{"name":"Rancho Zé Arvim"}}}