{"686921146":{"location":[35.0166162,-76.3151081],"ct":"US","tp":"CR","ts":"2019-10-09T03:02:14Z","tX":294,"tY":405,"tags":{"addr:city":"Cedar Island","addr:country":"US","addr:housenumber":"3557","addr:postcode":"28520","addr:state":"NC","addr:street":"Cedar Island Road","capacity":"61","caravans":"yes","email":"info@cedarislandresort.com","fee":"yes","internet_access":"wlan","internet_access:fee":"no","name":"Cedar Island RV Park","phone":"+1 252 515 0201","power_supply":"yes","sanitary_dump_station":"yes","tents":"yes","website":"https://cedarislandresort.com/rv-park?v=7516fd43adaa"}},"1092581637":{"location":[35.0047971,-76.3149665],"ct":"US","tp":"CR","ts":"2022-09-07T09:42:27Z","tX":294,"tY":405,"tags":{}},"5889628296":{"location":[35.0164502,-76.3154247],"ct":"US","tp":"SD","ts":"2019-09-13T18:57:04Z","tX":294,"tY":405,"tags":{"access":"customers","fee":"yes","water_point":"yes"}}}