{"11019432396":{"location":[54.3914535,84.510896],"ct":"RU","tp":"CS","ts":"2023-07-02T06:00:22Z","tX":752,"tY":326,"tags":{"backcountry":"yes","name":"Место для стоянки"}},"11019448266":{"location":[54.4186911,84.6514977],"ct":"RU","tp":"CS","ts":"2023-07-02T06:01:38Z","tX":752,"tY":326,"tags":{"backcountry":"yes"}},"11019448666":{"location":[54.4090364,84.6693604],"ct":"RU","tp":"CS","ts":"2023-07-02T06:02:41Z","tX":752,"tY":326,"tags":{"backcountry":"yes"}},"11019453394":{"location":[54.4177008,84.6950554],"ct":"RU","tp":"CS","ts":"2023-07-02T06:03:31Z","tX":752,"tY":326,"tags":{"backcountry":"yes"}}}