{"455194229":{"location":[-20.722183,139.515826],"ct":"AU","tp":"CR","ts":"2016-11-23T02:30:46Z","tX":908,"tY":572,"tags":{"fee":"yes","name":"Discovery Holiday Parks - Argylla (BIG4)","power_supply":"yes","website":"https://www.big4.com.au/caravan-parks/qld/mount-isa"}},"841525656":{"location":[-20.7080894,139.4945119],"ct":"AU","tp":"CS","ts":"2025-03-02T00:33:35Z","tX":908,"tY":572,"tags":{"addr:housenumber":"185-189","addr:street":"Little West Street","caravans":"yes","email":"mountisa@discoveryparks.com.au","name":"Copper City Caravan Park","phone:AU":"1800 456 661","shower":"yes","tents":"yes","toilets":"yes"}},"1269299615":{"location":[-20.6809966,139.4979416],"ct":"AU","tp":"CS","ts":"2024-04-05T07:44:10Z","tX":908,"tY":572,"tags":{"name":"AAOK Moondarra Caravan Park"}},"5760987221":{"location":[-20.724561,139.5098716],"ct":"AU","tp":"CR","ts":"2018-07-15T03:11:13Z","tX":908,"tY":572,"tags":{"name":"Mount Isa Caravan Park"}}}