{"1923082":{"location":[49.5463951,-56.0715088],"ct":"CA","tp":"CS","ts":"2011-12-19T22:17:37Z","tX":352,"tY":349,"tags":{"source":"NRCan-CanVec-8.0"}},"1923552":{"location":[49.4038992,-56.0839924],"ct":"CA","tp":"CS","ts":"2012-03-29T21:07:15Z","tX":352,"tY":349,"tags":{"source":"NRCan-CanVec-8.0"}},"583383610":{"location":[49.5104532,-56.1075947],"ct":"CA","tp":"CR","ts":"2018-04-25T01:00:09Z","tX":352,"tY":349,"tags":{}},"1780956323":{"location":[49.4034191,-56.0801203],"ct":"CA","tp":"CS","ts":"2012-06-08T22:18:49Z","tX":352,"tY":349,"tags":{"name":"Kona Beach"}},"5577481299":{"location":[49.5100209,-56.1072169],"ct":"CA","tp":"CR","ts":"2018-04-25T01:00:08Z","tX":352,"tY":349,"tags":{}},"5690685234":{"location":[49.5799223,-56.1889038],"ct":"CA","tp":"CR","ts":"2023-10-07T18:09:48Z","tX":352,"tY":349,"tags":{"addr:street":"Main Street","name":"Town of King's Point RV Park","toilets":"yes","website":"http://www.townofkingspoint.com/rv-park.asp"}},"6110719112":{"location":[49.4268887,-56.1030689],"ct":"CA","tp":"CR","ts":"2018-12-02T12:41:26Z","tX":352,"tY":349,"tags":{"name":"Goodyear Cove Park and Campground"}}}