{"9688009769":{"location":[40.1867793,-90.3518579],"ct":"US","tp":"CS","ts":"2024-04-20T18:09:53Z","tX":254,"tY":386,"tags":{"access":"customers","addr:city":"Browning","addr:housenumber":"14999","addr:postcode":"62624","addr:state":"IL","addr:street":"Reservoir Road","capacity:persons":"50","name":"Camp Emmanuel Dining Hall & Chapel","operator":"Camp Emmanuel LLC"}},"9688009770":{"location":[40.1873439,-90.3534547],"ct":"US","tp":"CR","ts":"2024-04-20T18:09:53Z","tX":254,"tY":386,"tags":{"addr:city":"Browning","addr:housenumber":"14999","addr:postcode":"62624","addr:state":"IL","addr:street":"Reservoir Road","capacity:caravans":"10","internet_access":"no","name":"Camp Emmanuel RV Park","power_supply":"no","sanitary_dump_station":"no","website":"CampEm.com"}}}