{"295803788":{"location":[45.5661451,7.8163039],"ct":"IT","tp":"CS","ts":"2022-03-19T12:53:51Z","tX":2136,"tY":1464,"tags":{"addr:city":"Settimo Vittone","addr:housenumber":"54","addr:postcode":"10010","addr:street":"Strada Statale 26 della Valle d'Aosta","contact:email":"info@campignmobarone.it","contact:facebook":"pages/Camping%20Mombaron/148146625387285","contact:instagram":"campingmombarone","contact:mobile":"+39 349 5591346","contact:phone":"+39 0125 757907","contact:tripadvisor":"https://www.tripadvisor.it/Hotel_Review-g2093415-d4225768-Reviews-Camping_Mombarone-Settimo_Vittone_Province_of_Turin_Piedmont","contact:website":"https://www.campingmombarone.it","ele":"280","internet_access":"wlan","name":"Camping Mombarone"}}}