{"700835597":{"location":[46.4761265,-114.9047807],"tp":"CS","tags":{"capacity":"20","caravans":"yes","name":"Jerry Johnson Campground","operator":"USFS","shower":"no","tents":"yes","toilets":"yes"}},"901434590":{"location":[46.50734625,-114.68677414999999],"tp":"CS","tags":{"caravans":"13","name":"White Sand Campground","operator":"US Forest Service","shower":"no","tents":"yes","toilets":"yes"}},"901434591":{"location":[46.509524400000004,-114.78338755],"tp":"CS","tags":{"capacity":"13","caravans":"yes","name":"Whitehouse Campground","operator":"US Forest Service","shower":"no","tents":"yes","toilets":"yes"}},"901434592":{"location":[46.51151085,-114.72218000000001],"tp":"CS","tags":{"caravans":"yes","name":"Powell Campground","operator":"US Forest Service","shower":"no","tents":"yes","toilets":"yes"}},"3881384932":{"location":[46.5127368,-114.6713882],"tp":"CS","tags":{"name":"First Beaver Ridge Spot"}},"3881398344":{"location":[46.5028353,-114.6693936],"tp":"CS","tags":{}},"3881398363":{"location":[46.5109783,-114.6734475],"tp":"CS","tags":{}},"3881401235":{"location":[46.4882171,-114.669284],"tp":"CS","tags":{}},"3881405975":{"location":[46.4964037,-114.6527089],"tp":"CS","tags":{}},"3884317651":{"location":[46.4529275,-114.7161392],"tp":"CS","tags":{}},"3884977296":{"location":[46.529897,-114.7008426],"tp":"CS","tags":{"name":"Bear camp"}},"3884983859":{"location":[46.5319847,-114.7623746],"tp":"CS","tags":{"name":"giant cedar"}},"12146993026":{"location":[46.3256703,-114.6515452],"tp":"CS","tags":{"name":"Elk Summit Campground"}}}