{"255259392":{"location":[34.8645246,-114.6308921],"ct":"US","tp":"CR","ts":"2023-06-21T06:52:45Z","tX":185,"tY":406,"tags":{"addr:city":"Needles","addr:housenumber":"3396","addr:postcode":"92363","addr:state":"CA","addr:street":"Needles Highway","internet_access":"wlan","name":"Fender's River Road Resort","phone":"+1 (760) 326-3423","website":"http://www.fendersresort.com"}},"255259394":{"location":[34.8689848,-114.6393855],"ct":"US","tp":"CR","ts":"2016-02-06T21:28:06Z","tX":185,"tY":406,"tags":{}},"396456834":{"location":[34.8689806,-114.6426943],"ct":"US","tp":"CR","ts":"2019-02-17T04:12:10Z","tX":185,"tY":406,"tags":{"addr:city":"Needles","addr:country":"US","addr:housenumber":"5400","addr:postcode":"92363","addr:state":"CA","addr:street":"National Old Trails Road","caravans":"yes","name":"Needles KOA","sanitary_dump_station":"yes","source":"Bing","website":"https://koa.com/campgrounds/needles/"}}}