{"5636885822":{"location":[56.0088129,28.4366451],"ct":"BY","tp":"CS","ts":"2024-11-08T15:48:30Z","tX":592,"tY":318,"tags":{"name":"Стаянка","name:be":"Стаянка","name:ru":"Стоянка"}},"6269704727":{"location":[56.0072875,28.4378749],"ct":"BY","tp":"CS","ts":"2019-02-10T14:53:03Z","tX":592,"tY":318,"tags":{"name":"Camping"}},"6673686701":{"location":[56.0497046,28.3853562],"ct":"BY","tp":"CS","ts":"2024-11-08T15:48:30Z","tX":592,"tY":318,"tags":{"int_name":"kempinh","name":"кемпінг","name:be":"кемпінг","name:en":"camping","name:pl":"kemping","name:ru":"кемпинг"}}}