{"52893705":{"location":[35.7533486,-118.4206217],"ct":"US","tp":"CS","ts":"2021-01-03T03:53:48Z","tX":175,"tY":402,"tags":{"attribution":"Kern_County_GIS","name":"Frandy Park Campground","source":"http://www.co.kern.ca.us/gis/Files/CountyZoning.zip"}},"638012315":{"location":[35.7971768,-118.4507066],"ct":"US","tp":"CS","ts":"2018-10-25T21:19:11Z","tX":175,"tY":402,"tags":{"name":"Headquarters Campground"}},"838052591":{"location":[35.857477,-118.4504294],"ct":"US","tp":"CS","ts":"2021-09-11T16:20:39Z","tX":175,"tY":402,"tags":{"name":"Corral Creek Campground"}},"838073288":{"location":[35.8244213,-118.4621721],"ct":"US","tp":"CS","ts":"2021-01-03T03:47:52Z","tX":175,"tY":402,"tags":{"name":"Chico Flat Dispersed Campground","website":"https://www.fs.usda.gov/recarea/sequoia/recarea/?recid=79676"}},"891338579":{"location":[35.9011921,-118.3739244],"ct":"US","tp":"CS","ts":"2021-01-02T20:05:56Z","tX":175,"tY":402,"tags":{"capacity":"41","name":"Horse Meadow Campground","operator":"Forest Service","website":"https://www.fs.usda.gov/recarea/sequoia/recarea/?recid=79717"}},"891340871":{"location":[35.8827418,-118.2790605],"ct":"US","tp":"CS","ts":"2021-01-02T20:18:20Z","tX":175,"tY":402,"tags":{"backcountry":"yes"}},"891340872":{"location":[35.8848157,-118.2606976],"ct":"US","tp":"CS","ts":"2021-01-02T20:18:20Z","tX":175,"tY":402,"tags":{"backcountry":"yes","name":"Little Manter Meadow Campground"}},"891398797":{"location":[35.8737256,-118.4570537],"ct":"US","tp":"CS","ts":"2021-08-27T20:51:07Z","tX":175,"tY":402,"tags":{"capacity":"37","fee":"yes","name":"Gold Ledge Campground","website":"https://www.fs.usda.gov/recarea/sequoia/recarea/?recid=79703"}},"891398801":{"location":[35.8287843,-118.4585747],"ct":"US","tp":"CS","ts":"2022-08-28T16:22:19Z","tX":175,"tY":402,"tags":{"name":"Hospital Flat Campground","opening_hours":"May-Sep","seasonal":"yes"}},"1285389012":{"location":[35.76188,-118.4227483],"ct":"US","tp":"CS","ts":"2024-05-22T04:36:06Z","tX":175,"tY":402,"tags":{"addr:housenumber":"13801","addr:street":"Sierra Way","caravans":"yes","check_date":"2024-05-21","dog":"leashed","drinking_water":"yes","fee":"yes","internet_access":"wlan","internet_access:fee":"customers","name":"Kern River Sequoia RV Resort","openfire":"yes","payment:cash":"yes","payment:mastercard":"yes","payment:visa":"yes","phone":"+1 760-376-6119","picnic_table":"yes","power_supply":"yes","reservation":"yes","sanitary_dump_station":"yes","shower":"yes","tents":"yes","toilets":"yes","website":"https://www.krsrvresort.com/"}},"4696406575":{"location":[35.8437369,-118.1629706],"ct":"US","tp":"CS","ts":"2021-08-27T20:51:07Z","tX":175,"tY":402,"tags":{"capacity":"13","name":"Long Valley Campground","website":"https://www.blm.gov/visit/long-valley-campground"}},"6013906950":{"location":[35.8030633,-118.4521174],"ct":"US","tp":"CS","ts":"2018-10-25T21:12:48Z","tX":175,"tY":402,"tags":{"fee":"yes","internet_access":"no","name":"Halfway Campground"}},"6593867487":{"location":[35.924898,-118.1491015],"ct":"US","tp":"CS","ts":"2022-02-02T14:39:51Z","tX":175,"tY":402,"tags":{"backcountry":"yes"}},"6893214386":{"location":[35.7632367,-118.4234591],"ct":"US","tp":"CS","ts":"2019-10-17T16:24:58Z","tX":175,"tY":402,"tags":{"addr:city":"Kernville","addr:housenumber":"14001","addr:postcode":"93238","addr:street":"Sierra Way","internet_access":"wlan","name":"Rivernook Campground","opening_hours":"Mo-Th 09:00-08:00; Fr-Sa 09:00-21:00; Su 09:00-18:00","phone":"+1-760-376-2705","website":"https://rivernookcampground.com/"}},"6939432586":{"location":[35.7835112,-118.4435748],"ct":"US","tp":"CS","ts":"2019-11-02T16:07:16Z","tX":175,"tY":402,"tags":{"name":"Montain River Camp grown"}},"7821269885":{"location":[35.8641537,-118.4475376],"ct":"US","tp":"CS","ts":"2020-08-17T22:09:34Z","tX":175,"tY":402,"tags":{}},"7821269886":{"location":[35.8614738,-118.4485473],"ct":"US","tp":"CS","ts":"2020-08-17T22:09:40Z","tX":175,"tY":402,"tags":{}},"7821270685":{"location":[35.8121313,-118.4558693],"ct":"US","tp":"CS","ts":"2024-03-22T20:08:28Z","tX":175,"tY":402,"tags":{"group_only":"yes","name":"Camp Three Campground","website":"https://www.fs.usda.gov/recarea/sequoia/recarea/?recid=79865"}}}