{"197216078":{"location":[42.8040362,-81.1769018],"ct":"CA","tp":"CS","ts":"2023-10-11T19:55:27Z","tX":281,"tY":377,"tags":{"source":"NRCan-CanVec-10.0"}},"564095582":{"location":[42.6568376,-81.0147467],"ct":"CA","tp":"CR","ts":"2018-02-25T19:42:29Z","tX":281,"tY":377,"tags":{"name":"Beeline Trailer Park #2"}},"564095590":{"location":[42.6586162,-81.0129821],"ct":"CA","tp":"CR","ts":"2018-02-25T19:20:34Z","tX":281,"tY":377,"tags":{"name":"Beeline Trailer Park #1"}},"1906198303":{"location":[42.7450678,-81.0401123],"ct":"CA","tp":"CS","ts":"2012-09-09T00:46:41Z","tX":281,"tY":377,"tags":{"source":"NRCan-CanVec-10.0"}},"5737238894":{"location":[42.6782547,-81.1082087],"ct":"CA","tp":"CS","ts":"2021-08-12T02:00:49Z","tX":281,"tY":377,"tags":{"material":"Campsite_#6"}},"5737239089":{"location":[42.6762453,-81.1078761],"ct":"CA","tp":"CS","ts":"2021-08-12T02:00:49Z","tX":281,"tY":377,"tags":{"material":"Campsite_#3","name":"Campsite 3"}},"5737239116":{"location":[42.6775093,-81.10694],"ct":"CA","tp":"CS","ts":"2021-08-12T02:00:49Z","tX":281,"tY":377,"tags":{"material":"Campsite_#5"}},"5737239121":{"location":[42.676969,-81.1071653],"ct":"CA","tp":"CS","ts":"2021-08-12T02:00:49Z","tX":281,"tY":377,"tags":{"material":"Campsite_#4","name":"Campsite 4"}},"5737239129":{"location":[42.6739836,-81.1087986],"ct":"CA","tp":"CS","ts":"2021-08-12T02:00:49Z","tX":281,"tY":377,"tags":{"material":"Campsite_#1","name":"Campsite 1"}},"8765562355":{"location":[42.6746538,-81.1088025],"ct":"CA","tp":"CS","ts":"2021-08-12T02:00:49Z","tX":281,"tY":377,"tags":{"name":"Campsite 2"}}}