{"303589352":{"location":[24.2733777,120.7890444],"ct":"TW","tp":"CR","ts":"2014-10-23T03:43:53Z","tX":855,"tY":440,"tags":{"access":"customers","capacity":"13","fee":"no","operator":"石岡堡農特產中心","parking":"surface"}},"308573460":{"location":[24.2867162,120.8693971],"ct":"TW","tp":"CS","ts":"2019-06-02T10:47:20Z","tX":855,"tY":440,"tags":{"name":"大安露營區"}},"308670098":{"location":[24.2853991,120.8694946],"ct":"TW","tp":"CS","ts":"2024-01-07T11:13:22Z","tX":855,"tY":440,"tags":{"name":"梧桐露營區"}},"440876455":{"location":[24.4093069,120.7783069],"ct":"TW","tp":"CS","ts":"2016-09-06T01:06:22Z","tX":855,"tY":440,"tags":{"name":"依杉林露營區"}},"466848194":{"location":[24.4293353,120.9141111],"ct":"TW","tp":"CS","ts":"2017-01-18T06:33:59Z","tX":855,"tY":440,"tags":{"name":"遊牧民族露營區"}},"468977868":{"location":[24.4171011,120.9274907],"ct":"TW","tp":"CS","ts":"2017-01-26T06:40:44Z","tX":855,"tY":440,"tags":{"name":"石水坊露營區"}},"475193072":{"location":[24.3742062,120.8793966],"ct":"TW","tp":"CS","ts":"2017-02-17T03:31:05Z","tX":855,"tY":440,"tags":{"name":"四季非露不可"}},"583832300":{"location":[24.4293104,120.9114413],"ct":"TW","tp":"CS","ts":"2020-02-02T04:10:35Z","tX":855,"tY":440,"tags":{"camp_site":"standard","name":"五鄰休閒露營區","phone":"+886 936104346","website":"https://www.facebook.com/wuyacamping.life/"}},"819000007":{"location":[24.4427768,120.8001819],"ct":"TW","tp":"CS","ts":"2020-06-24T07:15:47Z","tX":855,"tY":440,"tags":{"backcountry":"yes","name":"風山雅筑露營區"}},"826072368":{"location":[24.4858073,120.8653461],"ct":"TW","tp":"CS","ts":"2020-07-14T07:07:22Z","tX":855,"tY":440,"tags":{"name":"風山雅筑露營"}},"975336800":{"location":[24.3277984,120.700321],"ct":"TW","tp":"CS","ts":"2024-05-19T07:20:51Z","tX":855,"tY":440,"tags":{"name":"摩天輪營地"}},"1092310465":{"location":[24.3882834,120.8097686],"ct":"TW","tp":"CS","ts":"2022-09-06T09:46:47Z","tX":855,"tY":440,"tags":{"name":"半月彎露營區"}},"1092311974":{"location":[24.38688,120.8145623],"ct":"TW","tp":"CS","ts":"2022-09-07T07:04:21Z","tX":855,"tY":440,"tags":{"name":"景庭露營區"}},"1092532367":{"location":[24.3866101,120.8252871],"ct":"TW","tp":"CS","ts":"2022-09-07T06:23:12Z","tX":855,"tY":440,"tags":{"name":"琉璃秋境"}},"1092546434":{"location":[24.3876275,120.827919],"ct":"TW","tp":"CS","ts":"2023-01-03T10:55:34Z","tX":855,"tY":440,"tags":{"name":"雲霧灣灣"}},"1092546436":{"location":[24.3842539,120.8253455],"ct":"TW","tp":"CS","ts":"2022-09-07T07:00:35Z","tX":855,"tY":440,"tags":{"name":"悠活憶境"}},"1097909421":{"location":[24.3428165,120.8745271],"ct":"TW","tp":"CS","ts":"2022-09-26T08:19:01Z","tX":855,"tY":440,"tags":{"name":"滝貓谷 山林漫遊渡假村"}},"1144413646":{"location":[24.3053337,120.6529299],"ct":"TW","tp":"CS","ts":"2023-02-12T16:49:49Z","tX":855,"tY":440,"tags":{"access":"customers","fee":"yes","name":"水映親子露營區"}},"1204064396":{"location":[24.3275761,120.6177909],"ct":"TW","tp":"CS","ts":"2023-09-01T02:25:29Z","tX":855,"tY":440,"tags":{}},"1204064397":{"location":[24.3274919,120.6185411],"ct":"TW","tp":"CS","ts":"2023-09-01T02:25:29Z","tX":855,"tY":440,"tags":{}},"1204064398":{"location":[24.3266792,120.6182623],"ct":"TW","tp":"CS","ts":"2023-09-01T02:25:29Z","tX":855,"tY":440,"tags":{}},"4173918926":{"location":[24.3951111,120.7853275],"ct":"TW","tp":"CS","ts":"2023-11-17T13:46:47Z","tX":855,"tY":440,"tags":{"name":"不遠山莊"}},"4173945705":{"location":[24.3399117,120.8275483],"ct":"TW","tp":"CS","ts":"2016-05-09T06:33:14Z","tX":855,"tY":440,"tags":{"name":"山林鳥日子"}},"4510435994":{"location":[24.4445788,120.899377],"ct":"TW","tp":"CS","ts":"2016-11-19T12:52:20Z","tX":855,"tY":440,"tags":{}},"4740923022":{"location":[24.2287797,120.7873255],"ct":"TW","tp":"CS","ts":"2017-03-18T05:16:55Z","tX":855,"tY":440,"tags":{"addr:street":"崑南街","name":"四分之三","name:zh":"四分之三"}},"6033485228":{"location":[24.3046192,120.6542236],"ct":"TW","tp":"CS","ts":"2018-11-21T18:46:53Z","tX":855,"tY":440,"tags":{"name":"一鏡頭露營區"}},"6126019786":{"location":[24.2296906,120.8790537],"ct":"TW","tp":"CS","ts":"2018-12-09T06:49:26Z","tX":855,"tY":440,"tags":{"name":"森林小鹿"}},"7343438688":{"location":[24.470117,120.9361284],"ct":"TW","tp":"CS","ts":"2020-03-29T15:56:04Z","tX":855,"tY":440,"tags":{"name":"翩翩泰安GLAMPING"}},"8582876122":{"location":[24.3333983,120.8178405],"ct":"TW","tp":"CS","ts":"2021-04-01T13:14:08Z","tX":855,"tY":440,"tags":{"name":"水玉妮光 Garden Camping"}},"10698802696":{"location":[24.5192177,120.8868207],"ct":"TW","tp":"CS","ts":"2023-02-28T06:45:34Z","tX":855,"tY":440,"tags":{"name":"碳森林"}},"10933889343":{"location":[24.3063038,120.7477709],"ct":"TW","tp":"CS","ts":"2023-05-28T12:03:12Z","tX":855,"tY":440,"tags":{"name":"鳳凰山農場民宿"}}}