{"2699057309":{"location":[48.4203518,-121.122506],"tp":"CS","tags":{}},"3468588939":{"location":[48.4519208,-120.9918579],"tp":"CS","tags":{"access":"permit","backcountry":"yes","horse":"no","name":"Cottonwood Camp","openfire":"yes","operator":"North Cascades National Park","tents":"2","toilets":"yes"}},"9024022520":{"location":[48.2426667,-120.9556621],"tp":"CS","tags":{"backcountry":"yes"}},"12059706150":{"location":[48.4392907,-121.0462312],"tp":"CS","tags":{"backcountry":"yes","informal":"yes","name":"Kool-Aid Lake Camp","toilets":"no"}},"12059706151":{"location":[48.3917734,-121.0569268],"tp":"CS","tags":{"backcountry":"yes","informal":"yes","name":"Yang Yang Lakes Camp","toilets":"no"}},"12059706152":{"location":[48.3395954,-121.052078],"tp":"CS","tags":{"backcountry":"yes","informal":"yes","name":"White Rock Lakes Camp","toilets":"no"}}}