{"438300814":{"location":[44.6206048,-121.1351657],"ct":"US","tp":"CR","ts":"2016-08-21T17:31:08Z","tX":167,"tY":369,"tags":{"name":"Jefferson County RV Park"}},"438300827":{"location":[44.618594,-121.1323109],"ct":"US","tp":"CR","ts":"2016-08-21T17:31:09Z","tX":167,"tY":369,"tags":{"name":"Trails West RV Park"}},"555565221":{"location":[44.8147283,-121.0956699],"ct":"US","tp":"CS","ts":"2018-01-24T22:17:32Z","tX":167,"tY":369,"tags":{"name":"Trout Creek Campground","operator":"BLM"}},"555565222":{"location":[44.7695449,-121.2078313],"ct":"US","tp":"CS","ts":"2023-08-29T01:36:54Z","tX":167,"tY":369,"tags":{"caravans":"yes","drinking_water":"no","name":"Mecca Flat Campground","operator":"BLM","power_supply":"no","shower":"no","tents":"yes","toilets":"yes"}},"774545001":{"location":[44.6858334,-121.2365824],"ct":"US","tp":"CS","ts":"2020-02-19T08:47:45Z","tX":167,"tY":369,"tags":{"name":"Pelton Park Campground"}},"846961479":{"location":[44.59534,-121.1702322],"ct":"US","tp":"CR","ts":"2022-06-06T03:06:24Z","tX":167,"tY":369,"tags":{}},"7226784659":{"location":[44.6744935,-121.2327737],"ct":"US","tp":"CR","ts":"2020-02-19T08:47:45Z","tX":167,"tY":369,"tags":{"name":"Lake Simtustus Resort"}}}