{"334706073":{"location":[40.2149036,-121.1775278],"ct":"US","tp":"CS","ts":"2021-05-13T01:38:25Z","tX":167,"tY":386,"tags":{"name":"Almanor South Campground","operator":"United States Forest Service","website":"https://www.fs.usda.gov/recarea/lassen/recarea/?recid=11257"}},"942285719":{"location":[40.2185406,-121.1791003],"ct":"US","tp":"CS","ts":"2021-05-14T02:17:19Z","tX":167,"tY":386,"tags":{"name":"Almanor North Campground","operator":"USDA Forest Service"}},"3417659094":{"location":[40.2184687,-121.18783],"ct":"US","tp":"CS","ts":"2021-05-15T12:48:49Z","tX":167,"tY":386,"tags":{"charge":"30","fee":"yes","name":"Almanor Legacy Campground","operator":"United States Forest Service","payment:cash":"yes","payment:cheque":"yes","website":"https://www.fs.usda.gov/recarea/lassen/recarea/?recid=11258"}},"4894085422":{"location":[40.3117398,-121.1909216],"ct":"US","tp":"CS","ts":"2017-06-03T17:38:17Z","tX":167,"tY":386,"tags":{"internet_access":"wlan","name":"North Shore Campground","name:en":"North Shore Campground"}},"5788077053":{"location":[40.4185492,-121.1557542],"ct":"US","tp":"CS","ts":"2018-07-26T21:21:01Z","tX":167,"tY":386,"tags":{}},"5788077153":{"location":[40.43116,-121.1637147],"ct":"US","tp":"CS","ts":"2018-07-26T21:21:04Z","tX":167,"tY":386,"tags":{}},"7851829422":{"location":[40.1891718,-121.1186227],"ct":"US","tp":"CS","ts":"2020-08-28T04:03:42Z","tX":167,"tY":386,"tags":{}}}