{"4390849391":{"location":[2.5482121,-76.8652164],"ct":"CO","tp":"CS","ts":"2016-09-07T22:04:29Z","tX":293,"tY":504,"tags":{"name":"Hogar Comunitario Los Pinos","name:es":"Hogar Comunitario Los Pinos"}},"8779043217":{"location":[2.5369539,-76.9211977],"ct":"CO","tp":"CS","ts":"2021-05-29T14:35:40Z","tX":293,"tY":504,"tags":{}},"12329791369":{"location":[2.7673412,-76.9483287],"ct":"CO","tp":"CS","ts":"2025-02-08T01:41:35Z","tX":293,"tY":504,"tags":{"access":"yes","backcountry":"yes","camp_site":"basic","caravans":"no","name":"Alto de La Paz","name:es":"Alto de la Paz"}}}