{"697547163":{"location":[47.5305098,5.0642031],"ct":"FR","tp":"CS","ts":"2024-10-24T20:04:47Z","tX":2105,"tY":1431,"tags":{"access":"customers","addr:city":"Diénay","addr:postcode":"21120","alt_website":"https://club-du-soleil-de-dijon-et-dienay.jimdosite.com/","barrier":"fence","brand":"FFN","description":"Grand terrain de 3 hectares en lisière de forêt, sa maison d’accueil, ses équipements collectifs et ses adhérents vous attendent 365 jours par an !","name":"Club du Soleil de Dijon-Dienay","nudism":"yes","operator":"Club du Soleil de Dijon","website":"https://club-naturiste-du-soleil-de-dijon.com/"}}}