{"1318374741":{"location":[48.5529693,-1.5860915],"ct":"FR","tp":"CR","ts":"2024-09-26T12:07:51Z","tX":2029,"tY":1414,"tags":{"capacity":"10","caravan_site":"motorhome_stopover","caravan_site:type":"village","fee":"yes","name":"Aire de services de Sains","opening_hours":"24/7","picnic_area":"yes","power_supply":"yes","power_supply:fee":"no","sanitary_dump_station":"yes","tents":"no","toilets":"yes","water_point":"yes","water_point:fee":"no","website":"https://www.saint-malo-tourisme.com/offres/aire-de-services-de-sains-sains-fr-3711957/"}}}