{"18083868":{"location":[-30.114255,148.995375],"ct":"AU","tp":"CS","ts":"2024-09-25T01:34:47Z","tX":935,"tY":601,"tags":{"access":"customers","addr:postcode":"2386","addr:state":"NSW","addr:street":"Burren Bore Road","addr:suburb":"Burren Junction","bin":"yes","caravans":"yes","charge":"$5/n","dog":"leashed","fee":"yes","informal":"no","maxstay":"21 days","name":"Burren Junction Bore Camp Site","note":"closed during summer","operator":"Walgett Shire Council","parking":"surface","payment:cash":"yes","power_supply":"no","sanitary_dump_station":"yes","seasonal":"winter;spring;autumn","shower":"yes","source":"LIP Imagery Jun 2017","static_caravans":"no","surface":"unpaved","tents":"yes","toilets":"yes","website":"https://www.walgett.nsw.gov.au/Departments/Infrastructure-Compliance/Swimming-pools-bore-baths/Burren-Junction-Bore-Baths"}},"9644446798":{"location":[-30.1143032,148.9963153],"ct":"AU","tp":"SD","ts":"2024-09-25T01:34:47Z","tX":935,"tY":601,"tags":{"access":"yes","fee":"no","operator":"Walgett Shire Council"}}}