{"210267716":{"location":[47.0962386,2.1826937],"ct":"FR","tp":"CS","ts":"2014-09-25T12:38:02Z","tX":518,"tY":359,"tags":{"name":"Les Épicéas","operator":"Municipalité","phone":"+33 2 48 57 12 04","stars":"2"}},"482593147":{"location":[47.1352653,2.1618417],"ct":"FR","tp":"CS","ts":"2009-09-03T17:21:58Z","tX":518,"tY":359,"tags":{}},"643945671":{"location":[47.1480676,2.2193254],"ct":"FR","tp":"CS","ts":"2021-03-11T16:40:08Z","tX":518,"tY":359,"tags":{"name":"Camping de Mehun sur Yèvre","phone":"+33 2 48 57 44 51","stars":"2","website":"http://www.tourisme-mehun.com/Camping-municipal.html"}},"671375775":{"location":[47.0844242,2.3807864],"ct":"FR","tp":"CR","ts":"2024-10-23T15:41:52Z","tX":518,"tY":359,"tags":{"bbq":"no","capacity":"46","caravan_site":"motorhome_stopover","caravan_site:type":"town","caravans":"no","charge":"14.22 EUR","dog":"leashed","fee":"yes","internet_access":"yes","internet_access:fee":"no","maxlength":"9","name":"Camping-Car Park Bourges","network":"CAMPING-CAR PARK","opening_hours":"24/7","operator":"CAMPING-CAR PARK","power_supply":"yes","sanitary_dump_station":"yes","surface":"gravel","tents":"no","trailer":"no","website":"https://www.campingcarpark.com/fr_FR/sejour/aire-etape-camping-car/centre-val-de-loire/18-cher/bourges"}},"671375776":{"location":[47.0835165,2.3815592],"ct":"FR","tp":"SD","ts":"2019-02-18T22:27:14Z","tX":518,"tY":359,"tags":{"access":"yes","fee":"no","opening_hours":"24/7","sanitary_dump_station:round_drain":"yes"}},"907723025":{"location":[47.2182967,2.3232961],"ct":"FR","tp":"CR","ts":"2024-10-26T12:49:00Z","tX":518,"tY":359,"tags":{"access":"yes","addr:city":"Allogny","addr:postcode":"18110","addr:street":"Route de Bourges","capacity":"10","caravan_site":"motorhome_stopover","caravan_site:type":"picnic","description":"Aire de services avec stationnement pour 10 camping-cars, eau gratuite, vidange, pour pique-nique","fee":"no","name":"Aire Allogny","picnic_area":"yes","sanitary_dump_station:chemical_toilet":"yes","sanitary_dump_station:grey_water":"yes","sanitary_dump_station:round_drain":"yes","supervised":"no","water_point":"yes"}},"907760911":{"location":[47.1440736,2.2099935],"ct":"FR","tp":"CR","ts":"2024-11-20T22:48:48Z","tX":518,"tY":359,"tags":{"access":"yes","addr:city":"Mehun-sur-Yèvre","addr:postcode":"18500","addr:street":"Quai du canal","capacity":"10","caravan_site":"motorhome_stopover","caravan_site:type":"river","dog":"yes","fee":"no","internet_access":"no","maxstay":"no","name":"Mehun-sur-Yèvre Aire de Camping-Car","operator":"Ville de Mehun-sur-Yèvre","power_supply":"no","sanitary_dump_station":"yes","sanitary_dump_station:chemical_toilet":"yes","sanitary_dump_station:grey_water":"yes","sanitary_dump_station:round_drain":"yes","supervised":"no","water_point":"yes","water_point:fee":"yes","website":"https://www.valdeloire-france.com/aire-camping-car/aire-de-service-12/","wikimedia_commons":"Category:Mehun-sur-Yèvre Motorhome Stopover"}},"907766112":{"location":[47.1859843,2.4178896],"ct":"FR","tp":"CR","ts":"2024-05-24T16:36:08Z","tX":518,"tY":359,"tags":{"access":"yes","addr:city":"Saint-Georges-sur-Moulon","addr:postcode":"18110","addr:street":"Route de Coillard","capacity":"3","caravan_site":"motorhome_stopover","caravan_site:type":"lake;village","fee":"no","maxstay":"no","name":"Aire de Camping-car Saint-Georges-sur-Moulon","opening_hours":"Apr-Oct","operator":"Ville de Saint-Georges-sur-Moulon","power_supply":"no","sanitary_dump_station":"yes","sanitary_dump_station:chemical_toilet":"yes","sanitary_dump_station:grey_water":"yes","sanitary_dump_station:round_drain":"yes","seasonal":"spring;summer;autumn","supervised":"no","water_point":"yes","website":"https://www.valdeloire-france.com/aire-camping-car/aire-de-service-15/"}},"1125377254":{"location":[47.1972417,2.3995941],"ct":"FR","tp":"CS","ts":"2023-10-27T18:30:45Z","tX":518,"tY":359,"tags":{"name":"Camping Municipal les Plantes","stars":"2","website":"https://www.st-martin-auxigny.org/camping-les-plantes-602956.html"}},"1159052294":{"location":[47.0732776,2.3945157],"ct":"FR","tp":"CS","ts":"2024-10-08T06:55:26Z","tX":518,"tY":359,"tags":{"addr:housenumber":"26","addr:street":"Boulevard de l'Industrie","cabins":"yes","capacity:caravans":"84","caravans":"yes","contact:website":"https://www.aquadis-loisirs.com/camping-nature/camping-de-bourges","dog":"yes","email":"camping.bourges@aquadis-loisirs.com","fee":"yes","motorhome":"yes","name":"Camping de Bourges","old_name":"Le Robinson","operator":"Aquadis Loisirs","phone":"+33 2 48 20 16 85","power_supply":"yes","shower":"yes","stars":"3","tents":"yes","toilets":"yes"}},"4741772824":{"location":[47.0760333,2.3991468],"ct":"FR","tp":"CR","ts":"2024-10-12T23:08:50Z","tX":518,"tY":359,"tags":{"caravan_site":"motorhome_stopover","caravan_site:type":"town","fee":"no","name":"Aire Bourges Rue Jean Bouin","power_supply":"yes"}},"11931168871":{"location":[47.0850233,2.3779714],"ct":"FR","tp":"CR","ts":"2024-10-12T23:03:39Z","tX":518,"tY":359,"tags":{"caravan_site":"motorhome_stopover","caravan_site:type":"river","dog":"yes","fee":"no","maxstay":"48 hours","name":"Aire du Pré Doulet","power_supply":"no","sanitary_dump_station":"yes","tents":"no","website":"https://www.valdeloire-france.com/aire-camping-car/aire-de-service-du-pre-doulet/"}},"5632884565":{"location":[47.0946171,2.2411619],"ct":"FR","tp":"SD","ts":"2020-03-19T07:37:11Z","tX":518,"tY":359,"tags":{"description":"vidange eaux grises et noires, recharge eau et électricité, GRATUIT","fixme":"vérifier emplacement"}},"6578676966":{"location":[47.2190801,2.3231991],"ct":"FR","tp":"SD","ts":"2021-11-20T14:40:26Z","tX":518,"tY":359,"tags":{"description":"Station de vidange pour Camping-car.","fee":"no","operator":"Ville de Allogny","sanitary_dump_station:chemical_toilet":"yes","sanitary_dump_station:grey_water":"yes","sanitary_dump_station:round_drain":"yes","water_point":"yes"}},"8429113849":{"location":[47.1438382,2.2101263],"ct":"FR","tp":"SD","ts":"2024-11-20T22:48:48Z","tX":518,"tY":359,"tags":{"access":"yes","fee":"no","operator":"Ville de Mehun-sur-Yèvre.","sanitary_dump_station:chemical_toilet":"yes","sanitary_dump_station:grey_water":"yes","sanitary_dump_station:round_drain":"yes","water_point":"yes","wikimedia_commons":"File:Mehun-sur-Yèvre sanitary dump station.jpg"}},"8429116891":{"location":[47.1857449,2.4180591],"ct":"FR","tp":"SD","ts":"2021-11-20T14:40:26Z","tX":518,"tY":359,"tags":{"description":"Station de vidange pour Camping-car.","fee":"no","operator":"Ville de Saint-Georges-sur-Moulon","sanitary_dump_station:chemical_toilet":"yes","sanitary_dump_station:grey_water":"yes","sanitary_dump_station:round_drain":"yes","water_point":"yes"}},"10871411691":{"location":[47.0945513,2.2408788],"ct":"FR","tp":"SD","ts":"2023-05-05T17:36:16Z","tX":518,"tY":359,"tags":{"description":"borne FLOT BLEU","name":"Aire de Bourges"}}}