{"2837816512":{"location":[48.2852135,24.7389073],"ct":"UA","tp":"CS","ts":"2021-06-28T17:57:09Z","tX":582,"tY":354,"tags":{"backcountry":"yes"}},"4990499070":{"location":[48.3330516,24.6392187],"ct":"UA","tp":"CS","ts":"2020-04-02T22:59:43Z","tX":582,"tY":354,"tags":{"backcountry":"yes"}},"4990499073":{"location":[48.3236527,24.6518722],"ct":"UA","tp":"CS","ts":"2020-04-02T22:59:43Z","tX":582,"tY":354,"tags":{"backcountry":"yes"}},"4990499074":{"location":[48.3150137,24.6707041],"ct":"UA","tp":"CS","ts":"2020-04-02T22:59:43Z","tX":582,"tY":354,"tags":{"backcountry":"yes"}},"4990499104":{"location":[48.2872748,24.6936833],"ct":"UA","tp":"CS","ts":"2020-04-02T22:59:43Z","tX":582,"tY":354,"tags":{"backcountry":"yes"}},"4990601222":{"location":[48.2863673,24.695016],"ct":"UA","tp":"CS","ts":"2020-04-02T22:59:43Z","tX":582,"tY":354,"tags":{"backcountry":"yes"}},"6695546385":{"location":[48.2598078,24.6589504],"ct":"UA","tp":"CS","ts":"2023-09-30T11:06:50Z","tX":582,"tY":354,"tags":{"backcountry":"yes"}},"6696674286":{"location":[48.2775859,24.6236084],"ct":"UA","tp":"CS","ts":"2019-08-09T08:38:43Z","tX":582,"tY":354,"tags":{}},"6696674388":{"location":[48.2708271,24.6213124],"ct":"UA","tp":"CS","ts":"2019-08-09T08:39:09Z","tX":582,"tY":354,"tags":{}},"7360281872":{"location":[48.3519809,24.6115664],"ct":"UA","tp":"CS","ts":"2020-04-02T22:42:13Z","tX":582,"tY":354,"tags":{"backcountry":"yes"}},"7360305944":{"location":[48.2705451,24.6749544],"ct":"UA","tp":"CS","ts":"2024-02-29T12:40:07Z","tX":582,"tY":354,"tags":{"backcountry":"yes"}},"7865151333":{"location":[48.245336,24.7478775],"ct":"UA","tp":"CS","ts":"2021-05-13T10:34:27Z","tX":582,"tY":354,"tags":{"description":"Места на 4 палатки, до воды 200м, дрова есть."}},"7867819883":{"location":[48.2874317,24.6933369],"ct":"UA","tp":"CS","ts":"2020-09-02T09:59:26Z","tX":582,"tY":354,"tags":{"backcountry":"yes"}},"8005468823":{"location":[48.2857028,24.6960088],"ct":"UA","tp":"CS","ts":"2020-10-14T05:16:54Z","tX":582,"tY":354,"tags":{"backcountry":"yes"}},"8727845257":{"location":[48.4064815,24.7149459],"ct":"UA","tp":"CS","ts":"2021-05-13T10:34:29Z","tX":582,"tY":354,"tags":{"description":"Есть стол и скамейка, дрова, но нет воды."}},"8846783517":{"location":[48.2689932,24.7445571],"ct":"UA","tp":"CS","ts":"2023-09-05T07:12:28Z","tX":582,"tY":354,"tags":{"description":"Місце під намет","description:en":"Place for tent","description:uk":"Місце під намет"}},"8849704179":{"location":[48.2498349,24.6145086],"ct":"UA","tp":"CS","ts":"2021-06-20T06:04:49Z","tX":582,"tY":354,"tags":{"description":"Много места"}},"8959631417":{"location":[48.2759399,24.7346134],"ct":"UA","tp":"CS","ts":"2023-09-05T07:11:54Z","tX":582,"tY":354,"tags":{"description":"Місце для наметів","description:uk":"Місце для наметів"}},"8989953718":{"location":[48.273173,24.7095155],"ct":"UA","tp":"CS","ts":"2023-09-05T07:10:28Z","tX":582,"tY":354,"tags":{"description":"Місце під намет","description:uk":"Місце під намет"}},"8989953720":{"location":[48.2721913,24.6918063],"ct":"UA","tp":"CS","ts":"2023-09-30T11:06:50Z","tX":582,"tY":354,"tags":{"backcountry":"yes","description":"Столик, місце для намету, кострище","description:uk":"Столик, місце для намету, кострище"}},"8989957817":{"location":[48.2732337,24.7075528],"ct":"UA","tp":"CS","ts":"2023-09-05T07:10:28Z","tX":582,"tY":354,"tags":{"description":"Місце під намет","description:uk":"Місце під намет"}},"9026675618":{"location":[48.294057,24.6171415],"ct":"UA","tp":"CS","ts":"2023-03-12T20:51:00Z","tX":582,"tY":354,"tags":{"name":"Місце для кемпінгу з краєвидом на Чорногору","name:en":"Camping spot with a view over Chornohora","name:uk":"Місце для кемпінгу з краєвидом на Чорногору"}},"9907736703":{"location":[48.3943488,24.9124535],"ct":"UA","tp":"CS","ts":"2022-07-24T15:03:54Z","tX":582,"tY":354,"tags":{"backcountry":"yes"}},"9907736704":{"location":[48.390946,24.9119372],"ct":"UA","tp":"CS","ts":"2022-07-24T15:03:54Z","tX":582,"tY":354,"tags":{"backcountry":"yes"}},"9907736705":{"location":[48.3902295,24.9106296],"ct":"UA","tp":"CS","ts":"2022-07-24T15:03:54Z","tX":582,"tY":354,"tags":{"backcountry":"yes"}},"9907745665":{"location":[48.382694,24.9476878],"ct":"UA","tp":"CS","ts":"2022-07-24T15:03:54Z","tX":582,"tY":354,"tags":{"backcountry":"yes"}},"9907745666":{"location":[48.3819393,24.9421427],"ct":"UA","tp":"CS","ts":"2022-07-24T15:03:54Z","tX":582,"tY":354,"tags":{"backcountry":"yes"}},"11168823738":{"location":[48.2532157,24.7624305],"ct":"UA","tp":"CS","ts":"2023-09-05T07:09:08Z","tX":582,"tY":354,"tags":{}},"11168823739":{"location":[48.2731634,24.7081737],"ct":"UA","tp":"CS","ts":"2023-09-05T07:10:28Z","tX":582,"tY":354,"tags":{}},"11168833737":{"location":[48.2322869,24.7771673],"ct":"UA","tp":"CS","ts":"2023-09-05T07:42:21Z","tX":582,"tY":354,"tags":{"backcountry":"yes","description":"Місце для кемпінгу","description:uk":"Місце для кемпінгу"}},"11168841237":{"location":[48.2446227,24.7475658],"ct":"UA","tp":"CS","ts":"2023-09-05T07:43:45Z","tX":582,"tY":354,"tags":{"backcountry":"yes","description":"Місце для кемпінгу"}},"11168841337":{"location":[48.2727196,24.7113288],"ct":"UA","tp":"CS","ts":"2023-09-05T07:10:28Z","tX":582,"tY":354,"tags":{}},"11168841437":{"location":[48.2732638,24.7073395],"ct":"UA","tp":"CS","ts":"2023-09-05T07:10:28Z","tX":582,"tY":354,"tags":{}},"11168844437":{"location":[48.2613757,24.6707711],"ct":"UA","tp":"CS","ts":"2024-04-22T21:42:05Z","tX":582,"tY":354,"tags":{"name":"Місце для кемпінгу","name:uk":"Місце для кемпінгу"}},"11168844537":{"location":[48.2672962,24.6461378],"ct":"UA","tp":"CS","ts":"2024-04-22T21:42:05Z","tX":582,"tY":354,"tags":{"backcountry":"yes","name":"Місце для кемпінгу","name:uk":"Місце для кемпінгу"}},"11168856737":{"location":[48.2579112,24.6607136],"ct":"UA","tp":"CS","ts":"2023-09-05T07:47:53Z","tX":582,"tY":354,"tags":{"backcountry":"yes","description":"Місце для кемпінгу"}},"11676636870":{"location":[48.25054,24.7734333],"ct":"UA","tp":"CS","ts":"2024-02-29T13:08:55Z","tX":582,"tY":354,"tags":{}}}