{"3584886396":{"location":[-13.7628942,-71.2031652],"ct":"PE","tp":"CS","ts":"2016-05-12T12:37:17Z","tX":309,"tY":551,"tags":{"name":"Campamento gratis"}},"3584886993":{"location":[-13.8253046,-71.238571],"ct":"PE","tp":"CS","ts":"2015-06-10T04:34:18Z","tX":309,"tY":551,"tags":{}},"3584886994":{"location":[-13.8039623,-71.1696355],"ct":"PE","tp":"CS","ts":"2023-06-27T01:08:16Z","tX":309,"tY":551,"tags":{}},"3584886995":{"location":[-13.761747,-71.2172975],"ct":"PE","tp":"CS","ts":"2017-06-28T03:18:14Z","tX":309,"tY":551,"tags":{"name":"Campamento gratis - Otorongo"}},"4181097403":{"location":[-13.8168215,-71.2681042],"ct":"PE","tp":"CS","ts":"2016-05-12T12:37:22Z","tX":309,"tY":551,"tags":{"name":"Campamento gratis"}},"4187343596":{"location":[-13.8704651,-71.242306],"ct":"PE","tp":"CS","ts":"2016-06-18T23:49:54Z","tX":309,"tY":551,"tags":{"name":"rainbow mountain"}},"4511375889":{"location":[-13.7522401,-71.2743001],"ct":"PE","tp":"CS","ts":"2016-11-20T00:55:21Z","tX":309,"tY":551,"tags":{"name":"Campamento Upis","name:es":"Campamento Upis"}},"4939448024":{"location":[-13.7186546,-71.246552],"ct":"PE","tp":"CS","ts":"2017-06-28T03:18:16Z","tX":309,"tY":551,"tags":{"name":"Campamento Pacchanta","name:en":"Campamento Pacchanta","name:es":"Campamento Pacchanta"}},"5149329430":{"location":[-13.8411867,-71.2781466],"ct":"PE","tp":"CS","ts":"2023-04-08T19:25:44Z","tX":309,"tY":551,"tags":{"name":"Campamento Anantapata"}},"6294155183":{"location":[-13.8824783,-71.224207],"ct":"PE","tp":"CS","ts":"2019-02-21T18:58:45Z","tX":309,"tY":551,"tags":{}},"7058791654":{"location":[-13.752232,-71.2304299],"ct":"PE","tp":"CS","ts":"2019-12-15T23:07:46Z","tX":309,"tY":551,"tags":{"name":"camping Azul Cocha"}},"7058825087":{"location":[-13.8373835,-71.2735692],"ct":"PE","tp":"CS","ts":"2019-12-15T23:11:11Z","tX":309,"tY":551,"tags":{}},"7058825088":{"location":[-13.8580214,-71.2979805],"ct":"PE","tp":"CS","ts":"2019-12-15T23:11:14Z","tX":309,"tY":551,"tags":{}},"7955736485":{"location":[-13.8155296,-71.2712257],"ct":"PE","tp":"CS","ts":"2020-09-29T16:38:11Z","tX":309,"tY":551,"tags":{"name":"Campamento","name:en":"Free camping huts"}},"9995739518":{"location":[-13.7521028,-71.2749451],"ct":"PE","tp":"CS","ts":"2022-09-02T19:31:10Z","tX":309,"tY":551,"tags":{}},"11129060289":{"location":[-13.7173095,-71.2423087],"ct":"PE","tp":"CS","ts":"2023-08-20T04:09:13Z","tX":309,"tY":551,"tags":{"caravans":"no","opening_hours":"24/7","tents":"yes","wheelchair":"no"}},"11129177190":{"location":[-13.8099717,-71.1981471],"ct":"PE","tp":"CS","ts":"2023-08-20T05:24:37Z","tX":309,"tY":551,"tags":{"opening_hours":"24/7","wheelchair":"no"}},"11172993443":{"location":[-13.8985101,-71.3257392],"ct":"PE","tp":"CS","ts":"2023-09-06T21:41:32Z","tX":309,"tY":551,"tags":{}},"11396542469":{"location":[-13.804254,-71.2800539],"ct":"PE","tp":"CS","ts":"2023-12-05T17:54:57Z","tX":309,"tY":551,"tags":{"name":"Laguna Pucacocha"}},"12021303269":{"location":[-13.7977139,-71.2797558],"ct":"PE","tp":"CS","ts":"2024-06-29T22:08:05Z","tX":309,"tY":551,"tags":{"name":"Campamento","name:en":"Campsite","name:es":"Campamento"}}}